npc_mvr/__init__.py
npc_mvr/mvr.py
npc_mvr/py.typed
npc_mvr-0.1.15.dist-info/licenses/LICENSE
npc_mvr-0.1.15.dist-info/METADATA
npc_mvr-0.1.15.dist-info/WHEEL
npc_mvr-0.1.15.dist-info/top_level.txt
npc_mvr-0.1.15.dist-info/RECORD
