Metadata-Version: 2.4
Name: npc-mvr
Version: 0.1.15
Summary: Tools for reading raw video data from MindScope Neuropixels experiments, compatible with data in the cloud.
Author-email: Ben Hardcastle <ben.hardcastle@alleninstitue.org>
License: MIT
Project-URL: Repository, https://github.com/AllenInstitute/npc_mvr
Project-URL: Issues, https://github.com/AllenInstitute/npc_mvr/issues
Classifier: Development Status :: 3 - Alpha
Classifier: Programming Language :: Python :: 3
Classifier: Programming Language :: Python :: 3.9
Classifier: Programming Language :: Python :: 3.10
Classifier: Programming Language :: Python :: 3.11
Classifier: License :: OSI Approved :: MIT License
Classifier: Operating System :: Microsoft :: Windows
Classifier: Operating System :: POSIX :: Linux
Requires-Python: >=3.9
License-File: LICENSE
Requires-Dist: npc-io>=0.1.20
Requires-Dist: npc-sync>=0.1.25
Requires-Dist: opencv-python-headless>=4.9.0.80
Requires-Dist: typing-extensions>=4.9.0
Dynamic: license-file
